mkdocs_footermatter/__init__.py
mkdocs_footermatter/plugin.py
mkdocs_footermatter-1.4.0.dist-info/LICENSE
mkdocs_footermatter-1.4.0.dist-info/METADATA
mkdocs_footermatter-1.4.0.dist-info/WHEEL
mkdocs_footermatter-1.4.0.dist-info/entry_points.txt
mkdocs_footermatter-1.4.0.dist-info/top_level.txt
mkdocs_footermatter-1.4.0.dist-info/RECORD
