Metadata-Version: 2.1
Name: mkdocs-footermatter
Version: 1.4.0
Summary: A plugin to extract authors, created date and updated date from YAML frontmatter
Author-email: Sondre Grønås <mail@sondregronas.com>
License: MIT
Project-URL: homepage, https://github.com/sondregronas/mkdocs-footermatter
Project-URL: documentation, https://github.com/sondregronas/mkdocs-footermatter
Project-URL: repository, https://github.com/sondregronas/mkdocs-footermatter
Project-URL: issues, https://github.com/sondregronas/mkdocs-footermatter/issues
Project-URL: funding, https://github.com/sponsors/sondregronas
Keywords: mkdocs,markdown,footer,author,edited,created,frontmatter,obsidian
Classifier: Development Status :: 5 - Production/Stable
Classifier: License :: OSI Approved :: MIT License
Classifier: Programming Language :: Python
Classifier: Programming Language :: Python :: 3
Classifier: Programming Language :: Python :: 3 :: Only
Classifier: Topic :: Documentation
Classifier: Topic :: Software Development :: Documentation
Requires-Python: >=3.8
License-File: LICENSE
Requires-Dist: mkdocs >=1
Requires-Dist: pendulum
Provides-Extra: tests
Requires-Dist: pytest ; extra == 'tests'
